posthog_django/__init__.py
posthog_django/apps.py
posthog_django/cache.py
posthog_django/client.py
posthog_django/conf.py
posthog_django/events.py
posthog_django/feature_flags.py
posthog_django/middleware.py
posthog_django/utils.py
posthog_django/py.typed
posthog_django-0.1.0.dist-info/METADATA
posthog_django-0.1.0.dist-info/WHEEL
posthog_django-0.1.0.dist-info/RECORD
