Metadata-Version: 2.4
Name: posthog-django
Version: 0.1.0
Summary: Django integration helpers for the PostHog Python SDK.
Author-email: João Freires <joaofreires@tutanota.com>
License: MIT
Classifier: License :: OSI Approved :: MIT License
Classifier: Programming Language :: Python
Classifier: Programming Language :: Python :: 3
Classifier: Programming Language :: Python :: 3 :: Only
Classifier: Programming Language :: Python :: 3.10
Classifier: Programming Language :: Python :: 3.11
Classifier: Programming Language :: Python :: 3.12
Classifier: Typing :: Typed
Requires-Python: >=3.10
Requires-Dist: django>=4.2
Requires-Dist: posthog>=7.6.0
Provides-Extra: dev
Requires-Dist: pytest-django>=4.8.0; extra == 'dev'
Requires-Dist: pytest>=8.2.0; extra == 'dev'
Requires-Dist: ruff>=0.6.8; extra == 'dev'
Requires-Dist: uv>=0.4.30; extra == 'dev'
